{
  "kind": "collectionType",
  "collectionName": "institutions",
  "info": {
    "singularName": "institution",
    "pluralName": "institutions",
    "displayName": "Institution"
  },
  "options": {
    "draftAndPublish": true
  },
  "pluginOptions": {},
  "attributes": {
    "name_en": {
      "type": "string"
    },
    "name_ar": {
      "type": "string"
    },
    "description_en": {
      "type": "blocks"
    },
    "description_ar": {
      "type": "blocks"
    },
    "logo": {
      "type": "media",
      "multiple": false,
      "allowedTypes": [
        "images",
        "files",
        "videos",
        "audios"
      ]
    },
    "url": {
      "type": "string"
    },
    "location": {
      "type": "customField",
      "customField": "plugin::strapi-location-picker.location-picker",
      "options": {
        "info": true
      }
    }
  }
}
